saf/__init__.py
saf/__version__.py
saf/data/__init__.py
saf/data/config.py
saf/data/favicon.ico
saf/example/__init__.py
saf/example/api/__init__.py
saf/example/api/run.py
saf/example/api/send_email_script.py
saf/example/api/common/ExcelUtils.py
saf/example/api/common/YamlUtils.py
saf/example/api/common/__init__.py
saf/example/api/common/api_client.py
saf/example/api/common/logger.py
saf/example/api/config/__init__.py
saf/example/api/config/config.py
saf/example/api/testcases/__init__.py
saf/example/api/testcases/test_one_html_case_template.py
saf/example/app/__init__.py
saf/example/app/common/ExcelUtils.py
saf/example/app/common/YamlUtils.py
saf/example/app/common/__init__.py
saf/example/app/common/logger.py
saf/example/app/pageobject/__init__.py
saf/example/app/testcases/__init__.py
saf/example/app/testcases/conftest.py
saf/example/app/testcases/test_xiaobai_case_allure.py
saf/example/app/testcases/test_xiaobai_case_v1.py
saf/example/app/testcases/test_xiaobai_case_v2.py
saf/example/app/testcases/test_xiaobai_case_v3.py
saf/example/web/__init__.py
saf/example/web/main.py
saf/example/web/common/ExcelUtils.py
saf/example/web/common/YamlUtils.py
saf/example/web/common/__init__.py
saf/example/web/common/logger.py
saf/example/web/pageObjects/__init__.py
saf/example/web/testcases/__init__.py
saf/example/web/testcases/conftest.py
saf/example/web/testcases/test_xiaobai_case_allure.py
saf/example/web/testcases/test_xiaobai_case_v1.py
saf/example/web/testcases/test_xiaobai_case_v2.py
saf/example/web/testcases/test_xiaobai_case_v3.py
saf/templates/API_Project/README.md
saf/templates/API_Project/convert_ui.bat
saf/templates/API_Project/convert_ui.py
saf/templates/API_Project/convert_ui.sh
saf/templates/API_Project/init_env.bat
saf/templates/API_Project/init_env.sh
saf/templates/API_Project/pytest.ini
saf/templates/API_Project/requirements.txt
saf/templates/API_Project/run_testcases.bat
saf/templates/API_Project/run_testcases.py
saf/templates/API_Project/run_testcases.sh
xiaobaisaf-3.3.1.dist-info/LICENSE
xiaobaisaf-3.3.1.dist-info/METADATA
xiaobaisaf-3.3.1.dist-info/WHEEL
xiaobaisaf-3.3.1.dist-info/entry_points.txt
xiaobaisaf-3.3.1.dist-info/top_level.txt
xiaobaisaf-3.3.1.dist-info/RECORD
