Metadata-Version: 2.1
Name: xiaobaisaf
Version: 3.3.1
Summary: simple_automation_framework(简称：SAF)使用最简单的模式就可以实现需要功能和测试效果，也是xiaobaiauto2的简化版SAF继承了selenium、requests/httpx、appium、loguru、xiaobaiauto2、飞书机器人、钉钉机器人、企业微信机器人（暂时不支持）、禅道提单API
Home-page: https://gitee.com/xiaobaiOTS/simlpe_automation_framework
Author: xiaobaiTser
Author-email: 807447312@qq.com
Keywords: saf automation xiaobai xiaobaiauto2 test framework
Requires-Python: >3.8
License-File: LICENSE
Provides-Extra: all
Requires-Dist: pytest ; extra == 'all'
Requires-Dist: pytest-html ; extra == 'all'
Requires-Dist: pytest-xdist ; extra == 'all'
Requires-Dist: pytest-ordering ; extra == 'all'
Requires-Dist: pytest-assume ; extra == 'all'
Requires-Dist: allure-pytest ; extra == 'all'
Requires-Dist: allure-python-commons ; extra == 'all'
Requires-Dist: allure2-adaptor ; extra == 'all'
Requires-Dist: pytest-rerunfailures ; extra == 'all'
Requires-Dist: adbutils ; extra == 'all'
Requires-Dist: loguru ; extra == 'all'
Requires-Dist: matplotlib ; extra == 'all'
Requires-Dist: msvc-runtime ; extra == 'all'
Requires-Dist: psutil ; extra == 'all'
Requires-Dist: pillow ; extra == 'all'
Requires-Dist: xiaobaiauto2 ; extra == 'all'
Requires-Dist: pypinyin ; extra == 'all'
Requires-Dist: jmespath ; extra == 'all'
Requires-Dist: bs4 ; extra == 'all'
Requires-Dist: lxml ; extra == 'all'
Requires-Dist: prance ; extra == 'all'
Requires-Dist: click ; extra == 'all'
Requires-Dist: python-opencv ; extra == 'all'
Requires-Dist: JIRA ; extra == 'all'
Provides-Extra: api
Requires-Dist: pytest ; extra == 'api'
Requires-Dist: pytest-html ; extra == 'api'
Requires-Dist: pytest-xdist ; extra == 'api'
Requires-Dist: pytest-ordering ; extra == 'api'
Requires-Dist: pytest-assume ; extra == 'api'
Requires-Dist: allure-pytest ; extra == 'api'
Requires-Dist: allure-python-commons ; extra == 'api'
Requires-Dist: allure2-adaptor ; extra == 'api'
Requires-Dist: pytest-rerunfailures ; extra == 'api'
Requires-Dist: xiaobaiauto2 ; extra == 'api'
Requires-Dist: prance ; extra == 'api'
Provides-Extra: app
Requires-Dist: pytest ; extra == 'app'
Requires-Dist: pytest-html ; extra == 'app'
Requires-Dist: pytest-xdist ; extra == 'app'
Requires-Dist: pytest-ordering ; extra == 'app'
Requires-Dist: pytest-assume ; extra == 'app'
Requires-Dist: allure-pytest ; extra == 'app'
Requires-Dist: allure-python-commons ; extra == 'app'
Requires-Dist: allure2-adaptor ; extra == 'app'
Requires-Dist: pytest-rerunfailures ; extra == 'app'
Requires-Dist: adbutils ; extra == 'app'
Requires-Dist: xiaobaiauto2 ; extra == 'app'
Provides-Extra: dev
Requires-Dist: pytest ; extra == 'dev'
Requires-Dist: pytest-html ; extra == 'dev'
Requires-Dist: pytest-xdist ; extra == 'dev'
Requires-Dist: pytest-ordering ; extra == 'dev'
Requires-Dist: pytest-assume ; extra == 'dev'
Requires-Dist: allure-pytest ; extra == 'dev'
Requires-Dist: allure-python-commons ; extra == 'dev'
Requires-Dist: allure2-adaptor ; extra == 'dev'
Requires-Dist: pytest-rerunfailures ; extra == 'dev'
Provides-Extra: doc
Requires-Dist: sphinx ; extra == 'doc'
Requires-Dist: sphinx-rtd-theme ; extra == 'doc'
Requires-Dist: recommonmark ; extra == 'doc'
Requires-Dist: sphinx-markdown-tables ; extra == 'doc'
Requires-Dist: sphinxcontrib-napoleon ; extra == 'doc'
Provides-Extra: web
Requires-Dist: pytest ; extra == 'web'
Requires-Dist: pytest-html ; extra == 'web'
Requires-Dist: pytest-xdist ; extra == 'web'
Requires-Dist: pytest-ordering ; extra == 'web'
Requires-Dist: pytest-assume ; extra == 'web'
Requires-Dist: allure-pytest ; extra == 'web'
Requires-Dist: allure-python-commons ; extra == 'web'
Requires-Dist: allure2-adaptor ; extra == 'web'
Requires-Dist: pytest-rerunfailures ; extra == 'web'
Requires-Dist: xiaobaiauto2 ; extra == 'web'
Requires-Dist: pypinyin ; extra == 'web'
Requires-Dist: bs4 ; extra == 'web'
Requires-Dist: lxml ; extra == 'web'
Provides-Extra: xiaobaiauto2
Requires-Dist: xiaobaiauto2 ; extra == 'xiaobaiauto2'
